README.txt
setup.py
src/zif/__init__.py
src/zif.jsmin.egg-info/PKG-INFO
src/zif.jsmin.egg-info/SOURCES.txt
src/zif.jsmin.egg-info/dependency_links.txt
src/zif.jsmin.egg-info/namespace_packages.txt
src/zif.jsmin.egg-info/not-zip-safe
src/zif.jsmin.egg-info/requires.txt
src/zif.jsmin.egg-info/top_level.txt
src/zif/jsmin/__init__.py
src/zif/jsmin/css.py
src/zif/jsmin/javascript.py
src/zif/jsmin/jsmin.py
src/zif/jsmin/thirdparty/__init__.py
src/zif/jsmin/thirdparty/packer.py
