Metadata-Version: 1.0
Name: zif.jsmin
Version: 0.2
Summary: WSGI middleware for javascript compression.
Home-page: http://zif.svn.sourceforge.net/viewvc/zif/zif.jsmin
Author: Jim Washington
Author-email: jwashin@users.sourceforge.net
License: BSD
Keywords: jsmin wsgi middleware zope3
Platform: UNKNOWN
